setup.py
client/__init__.py
client/client.py
client/common/__init__.py
client/common/decos.py
client/common/descriptors.py
client/common/errors.py
client/common/metaclasses.py
client/common/utils.py
client/common/vars.py
client/unit_tests/__init__.py
client/unit_tests/sock_test.py
client/unit_tests/test_client.py
client/unit_tests/test_server.py
client/unit_tests/test_utils.py
mess_client_prj_Ruslan.egg-info/PKG-INFO
mess_client_prj_Ruslan.egg-info/SOURCES.txt
mess_client_prj_Ruslan.egg-info/dependency_links.txt
mess_client_prj_Ruslan.egg-info/requires.txt
mess_client_prj_Ruslan.egg-info/top_level.txt